fotom/__init__.py
fotom/embedding.py
fotom/fotom.pt
fotom/fotom.yaml
fotom/metrics.py
fotom/model.py
fotom/utils.py
fotom/tests/__init__.py
fotom/tests/test_fotom.py
fotom-1.1.0.dist-info/LICENSE
fotom-1.1.0.dist-info/METADATA
fotom-1.1.0.dist-info/WHEEL
fotom-1.1.0.dist-info/top_level.txt
fotom-1.1.0.dist-info/RECORD
