Metadata-Version: 2.1
Name: fotom
Version: 1.1.0
Summary: A pip package for FoToM (Foundational Topology Models), pretrained models for graph deep learning
Home-page: https://github.com/neutralpronoun/fotom
Author: neutralpronoun
Author-email: alexander.davies@bristol.ac.uk
Classifier: Programming Language :: Python
Classifier: Programming Language :: Python :: 3.6
License-File: LICENSE
Requires-Dist: arrow
Requires-Dist: binaryornot
Requires-Dist: certifi
Requires-Dist: chardet
Requires-Dist: charset-normalizer
Requires-Dist: click
Requires-Dist: contourpy
Requires-Dist: cookiecutter
Requires-Dist: cycler
Requires-Dist: filelock
Requires-Dist: fonttools
Requires-Dist: fsspec
Requires-Dist: idna
Requires-Dist: importlib-resources
Requires-Dist: Jinja2
Requires-Dist: joblib
Requires-Dist: kiwisolver
Requires-Dist: littleutils
Requires-Dist: markdown-it-py
Requires-Dist: MarkupSafe
Requires-Dist: matplotlib
Requires-Dist: mdurl
Requires-Dist: mpmath
Requires-Dist: networkx
Requires-Dist: numpy
Requires-Dist: ogb
Requires-Dist: outdated
Requires-Dist: packaging
Requires-Dist: pandas
Requires-Dist: Pillow
Requires-Dist: pip-chill
Requires-Dist: psutil
Requires-Dist: Pygments
Requires-Dist: pyparsing
Requires-Dist: python-dateutil
Requires-Dist: python-slugify
Requires-Dist: pytz
Requires-Dist: PyYAML
Requires-Dist: requests
Requires-Dist: rich
Requires-Dist: scikit-learn
Requires-Dist: scipy
Requires-Dist: six
Requires-Dist: sympy
Requires-Dist: text-unidecode
Requires-Dist: threadpoolctl
Requires-Dist: torch
Requires-Dist: torch-scatter
Requires-Dist: torch-sparse
Requires-Dist: torch-geometric
Requires-Dist: tqdm
Requires-Dist: types-python-dateutil
Requires-Dist: typing-extensions
Requires-Dist: tzdata
Requires-Dist: urllib3
Requires-Dist: zipp
